netscaler_certbot_hook/__init__.py
netscaler_certbot_hook/__main__.py
netscaler_certbot_hook/cli.py
netscaler_certbot_hook/nitro.py
netscaler_certbot_hook-1.0.3.dist-info/licenses/LICENSE
netscaler_certbot_hook-1.0.3.dist-info/METADATA
netscaler_certbot_hook-1.0.3.dist-info/WHEEL
netscaler_certbot_hook-1.0.3.dist-info/entry_points.txt
netscaler_certbot_hook-1.0.3.dist-info/top_level.txt
netscaler_certbot_hook-1.0.3.dist-info/RECORD
