Metadata-Version: 2.4
Name: netscaler-certbot-hook
Version: 1.0.3
Summary: Automated SSL certificate management for Citrix NetScaler ADC using Certbot
Author-email: Simon Lauger <simon@lauger.de>
License: MIT
Project-URL: Homepage, https://github.com/slauger/netscaler-certbot-hook
Project-URL: Documentation, https://github.com/slauger/netscaler-certbot-hook#readme
Project-URL: Repository, https://github.com/slauger/netscaler-certbot-hook
Project-URL: Issues, https://github.com/slauger/netscaler-certbot-hook/issues
Project-URL: Changelog, https://github.com/slauger/netscaler-certbot-hook/blob/master/CHANGELOG.md
Keywords: netscaler,citrix,adc,certbot,letsencrypt,ssl,certificate,automation
Classifier: Development Status :: 5 - Production/Stable
Classifier: Intended Audience :: System Administrators
Classifier: Programming Language :: Python :: 3
Classifier: Programming Language :: Python :: 3.8
Classifier: Programming Language :: Python :: 3.9
Classifier: Programming Language :: Python :: 3.10
Classifier: Programming Language :: Python :: 3.11
Classifier: Programming Language :: Python :: 3.12
Classifier: Operating System :: OS Independent
Classifier: Topic :: System :: Systems Administration
Classifier: Topic :: Security :: Cryptography
Classifier: Topic :: Utilities
Requires-Python: >=3.8
License-File: LICENSE
Requires-Dist: pyOpenSSL>=20.0.0
Requires-Dist: requests>=2.25.0
Dynamic: license-file
